pyInterfaz/__init__.py
pyInterfaz/pyInterfaz.py
pyInterfaz-0.2.0.dist-info/METADATA
pyInterfaz-0.2.0.dist-info/WHEEL
pyInterfaz-0.2.0.dist-info/top_level.txt
pyInterfaz-0.2.0.dist-info/RECORD
