Metadata-Version: 2.1
Name: pyInterfaz
Version: 0.2.0
Summary: Clases para controlar la interfaz
Home-page: https://github.com/astoctas/pyInterfaz
Author: Alejandro Lavagnino
Author-email: alejandro.lavagnino@gmail.com
License: UNKNOWN
Platform: UNKNOWN
Classifier: Programming Language :: Python :: 3.6
Classifier: License :: OSI Approved :: MIT License
Classifier: Operating System :: OS Independent
Requires-Python: >=3.6
Requires-Dist: pyMata4
